ovcrypt/__init__.py
ovcrypt/__main__.py
ovcrypt/config.py
ovcrypt/ovcrypt.py
ovcrypt-0.4.2.dist-info/METADATA
ovcrypt-0.4.2.dist-info/WHEEL
ovcrypt-0.4.2.dist-info/top_level.txt
ovcrypt-0.4.2.dist-info/RECORD
