Metadata-Version: 2.1
Name: ovcrypt
Version: 0.4.2
Summary: OvCrypt
Home-page: 
Author: Dmitry Yakovlev
Author-email: info@overhosting.ru
Requires-Python: >=3.5
Requires-Dist: rsa
Requires-Dist: beautifulsoup4
Requires-Dist: requests
Requires-Dist: oe_common
Requires-Dist: ovcfg
